panzer/__init__.py
panzer/binance_api_map.py
panzer/errors.py
panzer/keys.py
panzer/limits.py
panzer/logs.py
panzer/request.py
panzer/signatures.py
panzer/time.py
panzer/weights.py
tests/__init__.py
panzer-1.0.9.dist-info/LICENSE
panzer-1.0.9.dist-info/METADATA
panzer-1.0.9.dist-info/WHEEL
panzer-1.0.9.dist-info/top_level.txt
panzer-1.0.9.dist-info/RECORD
