Metadata-Version: 2.1
Name: panzer
Version: 1.0.9
Summary: REST API manager for Binance API. Manages weights and credentials simply and securely.
Home-page: https://github.com/nand0san/panzer
Author: nand0san
Author-email: 
Classifier: Development Status :: 3 - Alpha
Classifier: Intended Audience :: Developers
Classifier: Natural Language :: English
Classifier: Programming Language :: Python :: 3
Classifier: Programming Language :: Python :: 3.11
Classifier: License :: OSI Approved :: MIT License
Classifier: Operating System :: OS Independent
Requires-Python: >=3.11
License-File: LICENSE
Requires-Dist: py-cpuinfo (>=9.0.0)
Requires-Dist: pycryptodome (>=3.19.0)
Requires-Dist: pytz (>=2023.3.post1)
Requires-Dist: requests (>=2.31.0)
Requires-Dist: tqdm (>=4.66.1)
Requires-Dist: typing (~=3.7.4.3)
